{"Name": "bitcoind", "Repository": "ofawx/bitcoind", "Registry": "https://hub.docker.com/r/ofawx/bitcoind/", "Network": "bridge", "Privileged": "false", "Overview": "Support the Bitcoin network by hosting your own node! This template provides a full Bitcoin Core node, built in a verifiably trustless way.\n", "WebUI": "", "Icon": "https://github.com/ofawx/unraid-templates/raw/master/img/bitcoin.png", "PostArgs": "", "Networking": {"Mode": "bridge"}, "CategoryList": ["Tools-Utilities", "Network-Other", "Crypto"], "Sources": ["https://bitcoin.org/", "https://hub.docker.com/r/ofawx/bitcoind/"], "Keywords": ["bitcoind", ["Tools-Utilities", "Network-Other", "Crypto"]], "Requires": "", "Tag": "latest", "Config": {"Port": {"P2P TCP": {"value": "8333", "Name": "P2P TCP", "Target": "8333", "Default": "8333", "Mode": "tcp", "Description": "Port to listen for incoming node connections", "Type": "Port", "Display": "always", "Required": "true", "Mask": "false"}, "Local RPC": {"value": "8332", "Name": "Local RPC", "Target": "8332", "Default": "8332", "Mode": "tcp", "Description": "Port to listen for RPC connections (Optional)", "Type": "Port", "Display": "always", "Required": "false", "Mask": "false"}}, "Variable": {}, "Path": {"Data": {"value": "/mnt/user/bitcoin/core/", "Name": "Data", "Target": "/root/.bitcoin/", "Default": "/mnt/user/bitcoin/", "Mode": "rw", "Description": "Blockchain and database storage. Requires at least 500 GiB free disk.", "Type": "Path", "Display": "always", "Required": "true", "Mask": "false"}}, "Device": {}, "Label": {}}}