{"Name": "duckdns", "Repository": "lscr.io/linuxserver/duckdns", "Registry": "https://github.com/orgs/linuxserver/packages/container/package/duckdns", "DonateText": "Donations", "DonateLink": "https://www.linuxserver.io/donate", "DonateImg": "https://raw.githubusercontent.com/linuxserver/docker-templates/master/linuxserver.io/img/donate.png", "Network": "bridge", "Privileged": "false", "Support": "https://github.com/linuxserver/docker-duckdns/issues/new/choose", "GitHub": "https://github.com/linuxserver/docker-duckdns#application-setup", "ReadMe": "https://github.com/linuxserver/docker-duckdns#readme", "Project": "https://duckdns.org/", "Overview": "Duckdns(https://duckdns.org/) is a free service which will point a DNS (sub domains of duckdns.org) to an IP of your choice. The service is completely free, and doesn't require reactivation or forum posts to maintain its existence.", "WebUI": "", "TemplateURL": "https://raw.githubusercontent.com/linuxserver/templates/master/unraid/duckdns.xml", "Icon": "https://raw.githubusercontent.com/linuxserver/docker-templates/master/linuxserver.io/img/duckdns-logo.png", "Config": [{"@attributes": {"Name": "Appdata", "Target": "/config", "Default": "", "Mode": "rw", "Description": "Used in conjunction with logging to file.", "Type": "Path", "Display": "always", "Required": "false", "Mask": "false"}, "value": ""}, {"@attributes": {"Name": "SUBDOMAINS", "Target": "SUBDOMAINS", "Default": "subdomain1,subdomain2", "Description": "multiple subdomains allowed, comma separated, no spaces", "Type": "Variable", "Display": "always", "Required": "true", "Mask": "false"}, "value": ""}, {"@attributes": {"Name": "TOKEN", "Target": "TOKEN", "Default": "token", "Description": "DuckDNS token", "Type": "Variable", "Display": "always", "Required": "true", "Mask": "true"}, "value": ""}, {"@attributes": {"Name": "LOG_FILE", "Target": "LOG_FILE", "Default": "false", "Description": "Set to `true` to log to file (also need to map /config).", "Type": "Variable", "Display": "always", "Required": "false", "Mask": "false"}, "value": ""}, {"@attributes": {"Name": "PUID", "Target": "PUID", "Default": "99", "Description": "Container Variable: PUID", "Type": "Variable", "Display": "advanced", "Required": "true", "Mask": "false"}, "value": ""}, {"@attributes": {"Name": "PGID", "Target": "PGID", "Default": "100", "Description": "Container Variable: PGID", "Type": "Variable", "Display": "advanced", "Required": "true", "Mask": "false"}, "value": ""}, {"@attributes": {"Name": "UMASK", "Target": "UMASK", "Default": "022", "Description": "Container Variable: UMASK", "Type": "Variable", "Display": "advanced", "Required": "false", "Mask": "false"}, "value": ""}], "Repo": "linuxserver's Repository", "ChangeLogPresent": true, "CategoryList": ["Network-DNS", "Tools-Utilities"], "Video": "https://www.youtube.com/watch?v=1y06G853Udg", "LastUpdateScan": 1647914669, "LastUpdate": 1646841623, "FirstSeen": 1479358800, "topTrending": -0.664}