{"Name": "Enigmatica6", "Repository": "goobaroo/enigmatica6", "Registry": "https://hub.docker.com/repository/docker/goobaroo/enigmatica6", "Network": "bridge", "Privileged": "false", "Project": "https://www.curseforge.com/minecraft/modpacks/enigmatica6", "Overview": "Play with new mods and old favorites in Minecraft 1.16.5! Enigmatica 6 offers a boatload of custom content including quests![br][br]Setup:[br][li]You must accept the EULA by setting the [b]EULA[/b] variable to [span style='color: #00E800;']true[/span] or the install will fail.[br]Optional:[br][li]You can setup a comma separated list of players who will have admin privileges in game by setting [b]OPS[/b]", "WebUI": "", "TemplateURL": "https://raw.githubusercontent.com/Goobaroo/unraid-templates/master/enigmatica6_server.xml", "Icon": "https://raw.githubusercontent.com/Goobaroo/docker-enigmatica6/main/enigmatica6.png", "PostArgs": "", "Networking": {"Mode": "bridge"}, "CategoryList": ["GameServers"], "Sources": ["https://www.curseforge.com/minecraft/modpacks/enigmatica6", "https://hub.docker.com/repository/docker/goobaroo/enigmatica6"], "Keywords": ["enigmatica6"], "Requires": "", "Config": {"Port": {"Port": {"value": "25565", "Name": "Port", "Target": "25565", "Default": "25565", "Mode": "tcp", "Description": "Port for the server. Ignored if using a dedicated IP for the container.", "Type": "Port", "Display": "always", "Required": "true", "Mask": "false"}}, "Variable": {"EULA": {"value": "false", "Name": "EULA", "Target": "EULA", "Default": "false", "Mode": "", "Description": "By typing TRUE you are indicating your agreement to the EULA of Mojang. Read it at https://account.mojang.com/documents/minecraft_eula before accepting it.", "Type": "Variable", "Display": "always", "Required": "true", "Mask": "false"}, "MAX_RAM": {"value": "5G", "Name": "MAX_RAM", "Target": "MAX_RAM", "Default": "5G", "Mode": "", "Description": "Maximum memory for the server. Must end in G for gigabytes.", "Type": "Variable", "Display": "always", "Required": "true", "Mask": "false"}, "OPS": {"value": "", "Name": "OPS", "Target": "OPS", "Default": "", "Mode": "", "Description": "Comma separated list of players to have op capability", "Type": "Variable", "Display": "always", "Required": "false", "Mask": "false"}, "MOTD": {"value": "", "Name": "MOTD", "Target": "MOTD", "Default": "", "Mode": "", "Description": "Custom Message of the Day", "Type": "Variable", "Display": "always", "Required": "false", "Mask": "false"}}, "Path": {"Installed Location": {"value": "/mnt/user/appdata/enigmatica6/", "Name": "Installed Location", "Target": "/data", "Default": "/mnt/user/appdata/enigmatica6/", "Mode": "rw", "Description": "Path to store the installed server files.", "Type": "Path", "Display": "always", "Required": "true", "Mask": "false"}}, "Device": {}, "Label": {}}}