{"Name": "freepbx", "Repository": "tiredofit/freepbx:15-latest", "Registry": "https://hub.docker.com/r/tiredofit/freepbx/", "Network": "bridge", "Privileged": "false", "Project": "https://github.com/tiredofit/docker-freepbx/", "Overview": "FreePBX is a web-based open-source graphical user interface that manages Asterisk, a voice over IP and telephony server.", "WebUI": "http://[IP]:[PORT:80]/admin/", "TemplateURL": "https://raw.githubusercontent.com/A75G/docker-templates/master/templates/freepbx.xml", "Icon": "https://raw.githubusercontent.com/A75G/docker-templates/master/templates/icons/freepbx.png", "Repo": "A75G's Repository", "CategoryList": ["Productivity", "Network-Voip", "Network-Messenger"], "topTrending": -4.197, "topPerforming": 0.353, "Config": {"Port": {"HTTP": {"value": "8150", "Name": "HTTP", "Target": "80", "Default": "8150", "Mode": "tcp", "Description": "HTTP", "Type": "Port", "Display": "always", "Required": "false", "Mask": "false"}, "HTTPs": {"value": "4150", "Name": "HTTPs", "Target": "443", "Default": "4150", "Mode": "tcp", "Description": "HTTPs", "Type": "Port", "Display": "always", "Required": "false", "Mask": "false"}, "PJSIP": {"value": "5060", "Name": "PJSIP", "Target": "5060", "Default": "5060", "Mode": "udp", "Description": "PJSIP", "Type": "Port", "Display": "always", "Required": "false", "Mask": "false"}, "SIP": {"value": "5160", "Name": "SIP", "Target": "5160", "Default": "5160", "Mode": "udp", "Description": "SIP", "Type": "Port", "Display": "always", "Required": "false", "Mask": "false"}, "TLS SIP": {"value": "5161", "Name": "TLS SIP", "Target": "5161", "Default": "5161", "Mode": "tcp", "Description": "TLS SIP", "Type": "Port", "Display": "always", "Required": "false", "Mask": "false"}, "RTP Ports": {"value": "18000-20000", "Name": "RTP Ports", "Target": "18000-20000", "Default": "18000-20000", "Mode": "udp", "Description": "RTP Ports", "Type": "Port", "Display": "always", "Required": "false", "Mask": "false"}, "FOP": {"value": "4445", "Name": "FOP", "Target": "4445", "Default": "4445", "Mode": "tcp", "Description": "FOP", "Type": "Port", "Display": "always", "Required": "false", "Mask": "false"}}, "Variable": {"DB_EMBEDDED": {"value": "TRUE", "Name": "DB_EMBEDDED", "Target": "DB_EMBEDDED", "Default": "TRUE|FALSE", "Mode": "", "Description": "Allows you to use an internally provided MariaDB Server e.g. TRUE or FALSE", "Type": "Variable", "Display": "always", "Required": "false", "Mask": "false"}, "ENABLE_FAIL2BAN": {"value": "FALSE", "Name": "ENABLE_FAIL2BAN", "Target": "ENABLE_FAIL2BAN", "Default": "TRUE|FALSE", "Mode": "", "Description": "ENABLE_FAIL2BAN", "Type": "Variable", "Display": "always", "Required": "false", "Mask": "false"}, "Flash Operator Panel": {"value": "TRUE", "Name": "Flash Operator Panel", "Target": "ENABLE_FOP", "Default": "TRUE|FALSE", "Mode": "", "Description": "Enable Flash Operator Panel", "Type": "Variable", "Display": "always", "Required": "false", "Mask": "false"}, "ENABLE_SSL": {"value": "FALSE", "Name": "ENABLE_SSL", "Target": "ENABLE_SSL", "Default": "FALSE|TRUE", "Mode": "", "Description": "Enable HTTPs to serve SSL requests - Default FALSE", "Type": "Variable", "Display": "always", "Required": "false", "Mask": "false"}, "ENABLE_XMPP": {"value": "FALSE", "Name": "ENABLE_XMPP", "Target": "ENABLE_XMPP", "Default": "FALSE|TRUE", "Mode": "", "Description": "Enable XMPP Module with MongoDB - Default FALSE", "Type": "Variable", "Display": "always", "Required": "false", "Mask": "false"}, "INSTALL_ADDITIONAL_MODULES": {"value": "", "Name": "INSTALL_ADDITIONAL_MODULES", "Target": "INSTALL_ADDITIONAL_MODULES", "Default": "", "Mode": "", "Description": "Comma seperated list of modules to additionally install on first container startup", "Type": "Variable", "Display": "always", "Required": "false", "Mask": "false"}, "RTP_START": {"value": "18000", "Name": "RTP_START", "Target": "RTP_START", "Default": "18000", "Mode": "", "Description": "What port to start RTP Transmissions", "Type": "Variable", "Display": "always", "Required": "false", "Mask": "false"}, "RTP_FINISH": {"value": "20000", "Name": "RTP_FINISH", "Target": "RTP_FINISH", "Default": "20000", "Mode": "", "Description": "What port to end RTP Transmissions", "Type": "Variable", "Display": "always", "Required": "false", "Mask": "false"}, "TLS_CERT": {"value": "cert.pem", "Name": "TLS_CERT", "Target": "TLS_CERT", "Default": "cert.pem", "Mode": "", "Description": "TLS Certificate to drop in /certs for HTTPS if no reverse proxy", "Type": "Variable", "Display": "always", "Required": "false", "Mask": "false"}, "TLS_KEY": {"value": "key.pem", "Name": "TLS_KEY", "Target": "TLS_KEY", "Default": "key.pem", "Mode": "", "Description": "TLS Key to drop in /certs for HTTPS if no reverse proxy", "Type": "Variable", "Display": "always", "Required": "false", "Mask": "false"}}, "Path": {"Data": {"value": "/mnt/user/appdata/freepbx/data/", "Name": "Data", "Target": "/data", "Default": "/mnt/user/appdata/freepbx/data/", "Mode": "rw", "Description": "Data", "Type": "Path", "Display": "always", "Required": "false", "Mask": "false"}, "Log": {"value": "/mnt/user/appdata/freepbx/logs/", "Name": "Log", "Target": "/var/log", "Default": "", "Mode": "rw", "Description": "Log", "Type": "Path", "Display": "always", "Required": "false", "Mask": "false"}, "WWW": {"value": "/mnt/user/appdata/freepbx/www/", "Name": "WWW", "Target": "/var/www/html", "Default": "", "Mode": "rw", "Description": "WWW", "Type": "Path", "Display": "always", "Required": "false", "Mask": "false"}, "Certs": {"value": "/mnt/user/appdata/freepbx/certs/", "Name": "Certs", "Target": "/certs", "Default": "/mnt/user/appdata/freepbx/certs/", "Mode": "rw", "Description": "Certs", "Type": "Path", "Display": "always", "Required": "false", "Mask": "false"}, "DB Path": {"value": "/mnt/user/appdata/freepbx/db/", "Name": "DB Path", "Target": "/var/lib/mysql", "Default": "", "Mode": "rw", "Description": "DB Path", "Type": "Path", "Display": "always", "Required": "false", "Mask": "false"}}, "Device": {}, "Label": {}}}