{"Name": "golinks", "Repository": "prologic/golinks:latest", "Registry": "https://hub.docker.com/r/prologic/golinks/", "Network": "bridge", "Privileged": "false", "Project": "https://github.com/prologic/golinks", "Overview": "Self-hosted smart bookmark search engine.", "WebUI": "http://[IP]:[PORT:8000]", "TemplateURL": "https://raw.githubusercontent.com/A75G/docker-templates/master/templates/golinks.xml", "Icon": "https://raw.githubusercontent.com/A75G/docker-templates/master/templates/icons/golinks.png", "PostArgs": "", "Repo": "A75G's Repository", "CategoryList": ["Productivity", "Tools-Utilities"], "topTrending": -0.197, "topPerforming": 0.451, "Config": {"Port": {"Port": {"value": "8000", "Name": "Port", "Target": "8000", "Default": "8000", "Mode": "tcp", "Description": "Port", "Type": "Port", "Display": "always", "Required": "false", "Mask": "false"}}, "Variable": {}, "Path": {}, "Device": {}, "Label": {}}}