{"Name": "Logarr", "Repository": "monitorr/logarr-alpha", "Registry": "https://hub.docker.com/r/monitorr/logarr-alpha/", "Network": "bridge", "Privileged": "false", "Support": "https://forums.unraid.net/topic/87798-support-selfhostersnets-template-repository", "Project": "https://github.com/Monitorr/logarr/", "Overview": "Logarr is a self-hosted, single-page, log consolidation tool written in PHP", "WebUI": "http://[IP]:[PORT:80]", "TemplateURL": "https://raw.githubusercontent.com/selfhosters/unRAID-CA-templates/master/templates/logarr.xml", "Icon": "https://raw.githubusercontent.com/selfhosters/unRAID-CA-templates/master/templates/img/logarr.png", "DonateText": "Buy us a beer!", "DonateLink": "https://paypal.me/monitorrapp", "Config": [{"@attributes": {"Name": "WebUI", "Target": "80", "Default": "", "Mode": "tcp", "Description": "Container Port: 80", "Type": "Port", "Display": "always", "Required": "true", "Mask": "false"}, "value": ""}, {"@attributes": {"Name": "Config", "Target": "/app", "Default": "/mnt/user/appdata/Logarr", "Mode": "rw", "Description": "Container Path: /app", "Type": "Path", "Display": "advanced", "Required": "true", "Mask": "false"}, "value": ""}, {"@attributes": {"Name": "PUID", "Target": "PUID", "Default": "99", "Description": "Container Variable: PUID", "Type": "Variable", "Display": "advanced", "Required": "false", "Mask": "false"}, "value": ""}, {"@attributes": {"Name": "PGID", "Target": "PGID", "Default": "100", "Description": "Container Variable: PGID", "Type": "Variable", "Display": "advanced", "Required": "false", "Mask": "false"}, "value": ""}], "Repo": "Selfhosters Unraid Discord Repository", "RepoShort": "Selfhosters", "Beta": "true", "CategoryList": ["Tools-Utilities"], "Video": "https://www.youtube.com/watch?v=1y06G853Udg", "LastUpdateScan": 1647039800, "LastUpdate": 1580982453, "FirstSeen": 1574294677, "topTrending": -0.932, "topPerforming": 0.406}