{"Name": "MiniNote", "Repository": "n1try/mininote", "Registry": "https://hub.docker.com/r/n1try/mininote", "Network": "bridge", "Privileged": "false", "Project": "https://github.com/muety/mininote", "Overview": "DESCRIPTION\r\n", "WebUI": "http://[IP]:[PORT:3000]", "TemplateURL": "https://raw.githubusercontent.com/SmartPhoneLover/unraid-docker-templates/master/templates/MiniNote.xml", "Icon": "https://raw.githubusercontent.com/SmartPhoneLover/unraid-docker-templates/main/templates/icons/mininote.png", "PostArgs": "", "Requires": "", "Repo": "SmartPhoneLover's Repository", "Beta": "true", "CategoryList": ["Productivity", "Tools-Utilities"], "Config": {"Port": {"WebUI": {"value": "3000", "Name": "WebUI", "Target": "3000", "Default": "", "Mode": "tcp", "Description": "", "Type": "Port", "Display": "always", "Required": "false", "Mask": "false"}}, "Variable": {}, "Path": {"Storage (data)": {"value": "/mnt/user/appdata/mininote", "Name": "Storage (data)", "Target": "/app/data", "Default": "", "Mode": "rw", "Description": "", "Type": "Path", "Display": "always", "Required": "false", "Mask": "false"}}, "Device": {}, "Label": {}}}