{"Name": "MotionEye", "Repository": "malvarez00/docker-motioneye", "Registry": "https://hub.docker.com/r/malvarez00/docker-motioneye", "Network": "bridge", "Privileged": "false", "Support": "https://forums.lime-technology.com/topic/61014-support-malvarez00-motioneye/", "Overview": "MotionEye Docker&lt;br /&gt;\r\nA surveillance solution base on: MotionEye, Motion and Docker.&lt;br /&gt;\r\n&lt;br /&gt;\r\nIt's easy and ready to use. Just configure a camera and run this docker, then videos and images will be saved once a motion is detected while a notification e-mail including the recorded video and a preview image will be sent. On top of that, the webcam can be accessed anytime via HTTP live streaming.&lt;br /&gt;\r\n&lt;br /&gt;\r\nDefault Username: admin&lt;br /&gt;\r\nDefault Password: BLANK&lt;br /&gt;\r\n&lt;br/&gt;\r\nRoot Directory \"/var/lib/motioneye/", "WebUI": "http://[IP]:[PORT:8765]", "TemplateURL": "https://raw.githubusercontent.com/malvarez00/unRAID-Docker-Templates/master/malvarez00/MotionEye.xml", "Icon": "https://raw.githubusercontent.com/malvarez00/unRAID-Docker-Templates/master/malvarez00/icons/motioneye_96x96.png", "PostArgs": "", "DonateImg": "", "MinVer": "", "Networking": {"Mode": "bridge"}, "Repo": "malvarez00's Repository", "CategoryList": ["Network"], "Video": "https://www.youtube.com/watch?v=1y06G853Udg", "LastUpdateScan": 1647068593, "LastUpdate": 1583381054, "FirstSeen": "1519440420", "topTrending": 0.359, "topPerforming": 2.492, "Config": {"Port": {"WEB UI": {"value": "8765", "Name": "WEB UI", "Target": "8765", "Default": "8765", "Mode": "tcp", "Description": "Container Port: 8765", "Type": "Port", "Display": "always-hide", "Required": "false", "Mask": "false"}}, "Variable": {"Key 1": {"value": "99", "Name": "Key 1", "Target": "PUID", "Default": "99", "Mode": "", "Description": "Container Variable: PUID", "Type": "Variable", "Display": "always", "Required": "true", "Mask": "false"}, "Key 2": {"value": "100", "Name": "Key 2", "Target": "PGID", "Default": "100", "Mode": "", "Description": "Container Variable: PGID", "Type": "Variable", "Display": "always", "Required": "true", "Mask": "false"}}, "Path": {"Configuration Path": {"value": "/mnt/cache/appdata/MotionEye/config", "Name": "Configuration Path", "Target": "/etc/motioneye", "Default": "/mnt/cache/appdata/MotionEye/config", "Mode": "rw", "Description": "Container Path: /etc/motioneye", "Type": "Path", "Display": "always-hide", "Required": "true", "Mask": "false"}, "Media Files Path": {"value": "/mnt/user/data/MotionEye", "Name": "Media Files Path", "Target": "/var/lib/motioneye", "Default": "/mnt/user/appdata/MotionEye/media", "Mode": "rw", "Description": "Container Path: /var/lib/motioneye", "Type": "Path", "Display": "always-hide", "Required": "true", "Mask": "false"}}, "Device": {}, "Label": {}}}