{"Name": "petio", "Repository": "ghcr.io/petio-team/petio", "Registry": "https://registry.hub.docker.com/r/ghcr.io/petio-team/petio", "Branch": [{"Tag": "latest", "TagDescription": "Latest fully stable release of Petio"}, {"Tag": "preview", "TagDescription": "Latest stable testing release of Petio"}, {"Tag": "dev", "TagDescription": "Latest unstable dev release of Petio"}], "Network": "bridge", "Privileged": "false", "Support": "https://discord.gg/bseGmrUd3N", "Project": "https://github.com/petio-team/petio", "Overview": "Petio is a third party companion app available to Plex server owners to allow their users to request, review and discover content", "WebUI": "http://[IP]:[PORT:7777]", "TemplateURL": "https://raw.githubusercontent.com/PotentialIngenuity/petio-unraid/master/petio.xml", "Icon": "https://github.com/PotentialIngenuity/petio-unraid/raw/master/petio.png", "PostArgs": "", "Repo": "ChargingCosmonaut's Repository", "Video": "https://www.youtube.com/watch?v=1y06G853Udg", "LastUpdateScan": 1647381815, "FirstSeen": 1616197385, "Config": {"Port": {"WebUI Port": {"value": "", "Name": "WebUI Port", "Target": "7777", "Default": "7777", "Mode": "", "Description": "", "Type": "Port", "Display": "always", "Required": "false", "Mask": "false"}}, "Variable": {}, "Path": {"Config Path": {"value": "", "Name": "Config Path", "Target": "/app/api/config", "Default": "/mnt/user/appdata/petio/config", "Mode": "rw", "Description": "", "Type": "Path", "Display": "always", "Required": "true", "Mask": "false"}, "Logs Path": {"value": "", "Name": "Logs Path", "Target": "/app/logs", "Default": "/mnt/user/appdata/petio/logs", "Mode": "rw", "Description": "", "Type": "Path", "Display": "always", "Required": "true", "Mask": "false"}}, "Device": {}, "Label": {}}}