{"Name": "pixapop", "Repository": "lscr.io/linuxserver/pixapop", "Registry": "https://github.com/orgs/linuxserver/packages/container/package/pixapop", "DonateText": "Donations", "DonateLink": "https://www.linuxserver.io/donate", "DonateImg": "https://raw.githubusercontent.com/linuxserver/docker-templates/master/linuxserver.io/img/donate.png", "Network": "bridge", "Privileged": "false", "Support": "https://github.com/linuxserver/docker-pixapop/issues/new/choose", "GitHub": "https://github.com/linuxserver/docker-pixapop#application-setup", "ReadMe": "https://github.com/linuxserver/docker-pixapop#readme", "Project": "https://github.com/bierdok/pixapop", "Overview": "Pixapop(https://github.com/bierdok/pixapop) is an open-source single page application to view your photos in the easiest way possible.", "WebUI": "http://[IP]:[PORT:80]", "TemplateURL": "https://raw.githubusercontent.com/linuxserver/templates/master/unraid/pixapop.xml", "Icon": "https://raw.githubusercontent.com/linuxserver/docker-templates/master/linuxserver.io/img/pixapop-logo.png", "Repo": "linuxserver's Repository", "ChangeLogPresent": true, "Video": "https://www.youtube.com/watch?v=1y06G853Udg", "LastUpdateScan": 1647914829, "LastUpdate": 1647328403, "FirstSeen": 1634990599, "Config": {"Port": {"WebUI": {"value": "", "Name": "WebUI", "Target": "80", "Default": "80", "Mode": "tcp", "Description": "WebUI", "Type": "Port", "Display": "always", "Required": "true", "Mask": "false"}}, "Variable": {"APP_USERNAME": {"value": "", "Name": "APP_USERNAME", "Target": "APP_USERNAME", "Default": "admin", "Description": "Specify a username to enable authentication.", "Type": "Variable", "Display": "always", "Required": "false", "Mask": "false"}, "APP_PASSWORD": {"value": "", "Name": "APP_PASSWORD", "Target": "APP_PASSWORD", "Default": "admin", "Description": "Specify a password to enable authentication.", "Type": "Variable", "Display": "always", "Required": "false", "Mask": "true"}, "PUID": {"value": "", "Name": "PUID", "Target": "PUID", "Default": "99", "Description": "Container Variable: PUID", "Type": "Variable", "Display": "advanced", "Required": "true", "Mask": "false"}, "PGID": {"value": "", "Name": "PGID", "Target": "PGID", "Default": "100", "Description": "Container Variable: PGID", "Type": "Variable", "Display": "advanced", "Required": "true", "Mask": "false"}, "UMASK": {"value": "", "Name": "UMASK", "Target": "UMASK", "Default": "022", "Description": "Container Variable: UMASK", "Type": "Variable", "Display": "advanced", "Required": "false", "Mask": "false"}}, "Path": {"Appdata": {"value": "", "Name": "Appdata", "Target": "/config", "Default": "", "Mode": "rw", "Description": "Stores config and logs for nginx base.", "Type": "Path", "Display": "advanced", "Required": "true", "Mask": "false"}, "Path: /photos": {"value": "", "Name": "Path: /photos", "Target": "/photos", "Default": "", "Mode": "rw", "Description": "Your local folder of photos.", "Type": "Path", "Display": "always", "Required": "true", "Mask": "false"}}, "Device": {}, "Label": {}}}