{"Name": "protonmail-bridge", "Repository": "shenxn/protonmail-bridge", "Registry": "https://hub.docker.com/r/shenxn/protonmail-bridge", "Network": "bridge", "Privileged": "false", "Project": "https://github.com/shenxn/protonmail-bridge-docker", "Overview": "ProtonMail Bridge for e-mail clients.\n\nAfter the container has started you will need to access the CLI to do the initial setup.\nFrom unraid terminal and run the following:\n```bash\ndocker exec -it protonmail-bridge /bin/bash\nchmod +x entrypoint.sh\n./entrypoint.sh init\n```\nWait for the bridge to startup, use `login` command and follow the instructions to add your account into the bridge. Then use  `info` to see the configuration information (username and password). After that, use `exit` to exit the bridge.\n\nYou may need CTRL+C to exit the docker entirely.\nThen restart the container.", "TemplateURL": "https://raw.githubusercontent.com/selfhosters/unRAID-CA-templates/master/templates/protonmail-bridge.xml", "Icon": "https://github.com/protonmail.png", "Config": [{"@attributes": {"Name": "Host Port 1", "Target": "25", "Default": "", "Mode": "tcp", "Description": "Container Port: 25", "Type": "Port", "Display": "always", "Required": "false", "Mask": "false"}, "value": ""}, {"@attributes": {"Name": "Host Port 2", "Target": "143", "Default": "", "Mode": "tcp", "Description": "Container Port: 143", "Type": "Port", "Display": "always", "Required": "false", "Mask": "false"}, "value": ""}, {"@attributes": {"Name": "appdata", "Target": "/root", "Default": "/mnt/user/appdata/protonmail-bridge/", "Mode": "rw", "Description": "Container Path: /root", "Type": "Path", "Display": "always", "Required": "true", "Mask": "false"}, "value": ""}], "Repo": "Selfhosters Unraid Discord Repository", "RepoShort": "Selfhosters", "Video": "https://www.youtube.com/watch?v=1y06G853Udg", "LastUpdateScan": 1648692216, "LastUpdate": 1648686345, "FirstSeen": 1609715259, "topTrending": -4.605, "topPerforming": 0.531}