{"Name": "tachidesk-docker", "Repository": "ghcr.io/suwayomi/tachidesk", "Registry": "https://github.com/suwayomi/docker-tachidesk", "Network": "bridge", "Privileged": "false", "Overview": "The official Tachidesk Docker-Container.\r\n", "WebUI": "http://[IP]:[PORT:4567]", "Icon": "https://raw.githubusercontent.com/Suwayomi/Tachidesk-Server/master/server/src/main/resources/icon/faviconlogo.png", "CategoryList": ["MediaServer-Other"], "Sources": ["https://github.com/Suwayomi/Tachidesk-Server", "https://github.com/suwayomi/docker-tachidesk"], "Keywords": ["tachidesk-docker", ["MediaServer-Other"]], "Requires": "", "Tag": "latest", "Config": {"Port": {"Port for WebUI": {"value": "4567", "Name": "Port for WebUI", "Target": "4567", "Default": "4567", "Mode": "tcp", "Description": "Port to connect to WebUI.\r\nStandard 4567.", "Type": "Port", "Display": "always", "Required": "true", "Mask": "false"}}, "Variable": {}, "Path": {"Appdata": {"value": "/mnt/user/appdata/Tachidesk-Docker", "Name": "Appdata", "Target": "/home/suwayomi/.local/share/Tachidesk", "Default": "/mnt/user/appdata/Tachidesk-Docker", "Mode": "rw", "Description": "Tachidesk stores its files here.", "Type": "Path", "Display": "always", "Required": "true", "Mask": "false"}, "Library": {"value": "", "Name": "Library", "Target": "/home/suwayomi/.local/share/Tachidesk/downloads", "Default": "", "Mode": "rw", "Description": "(Optional) Path to where your Downloads should be stored.\r\nDefault is in Appdata folder.", "Type": "Path", "Display": "always", "Required": "false", "Mask": "false"}, "Local-Library": {"value": "", "Name": "Local-Library", "Target": "/home/suwayomi/.local/share/Tachidesk/local", "Default": "", "Mode": "rw", "Description": "(Optional) You can add your local Library here.\r\nShould work like standard Tachiyomi.\r\n(https://tachiyomi.org/help/guides/local-manga/)", "Type": "Path", "Display": "always", "Required": "false", "Mask": "false"}}, "Device": {}, "Label": {}}}