{"Name": "unpackerr", "Repository": "cr.hotio.dev/hotio/unpackerr", "Registry": "https://hub.docker.com/r/hotio/unpackerr", "Branch": [{"Tag": "release", "TagDescription": "Releases", "Repository": "cr.hotio.dev/hotio/unpackerr:release", "Registry": "https://hub.docker.com/r/hotio/unpackerr"}, {"Tag": "testing", "TagDescription": "Pre-releases", "Repository": "cr.hotio.dev/hotio/unpackerr:testing", "Registry": "https://hub.docker.com/r/hotio/unpackerr"}, {"Tag": "nightly", "TagDescription": "Every commit to master branch", "Repository": "cr.hotio.dev/hotio/unpackerr:nightly", "Registry": "https://hub.docker.com/r/hotio/unpackerr"}], "Privileged": "false", "Project": "https://hotio.dev/containers/unpackerr", "Icon": "https://hotio.dev/webhook-avatars/unpackerr.png", "Overview": "Unpackerr extracts your Sonarr/Radarr/Lidarr torrent files.", "WebUI": "", "PostArgs": "", "Network": "bridge", "Repo": "hotio's Repository", "caTemplateURL": "https://raw.githubusercontent.com/hotio/unraid-templates/master/hotio/unpackerr.xml", "CategoryList": ["Downloaders", "Other"], "Config": {"Port": {}, "Variable": {"PUID": {"value": "", "Name": "PUID", "Target": "PUID", "Default": "99", "Mode": "", "Description": "Container Variable: PUID", "Type": "Variable", "Display": "advanced-hide", "Required": "false", "Mask": "false"}, "PGID": {"value": "", "Name": "PGID", "Target": "PGID", "Default": "100", "Mode": "", "Description": "Container Variable: PGID", "Type": "Variable", "Display": "advanced-hide", "Required": "false", "Mask": "false"}, "UMASK": {"value": "", "Name": "UMASK", "Target": "UMASK", "Default": "002", "Mode": "", "Description": "Container Variable: UMASK", "Type": "Variable", "Display": "advanced-hide", "Required": "false", "Mask": "false"}}, "Path": {"Host Path for /config": {"value": "", "Name": "Host Path for /config", "Target": "/config", "Default": "", "Mode": "rw", "Description": "Container Path: /config", "Type": "Path", "Display": "always-hide", "Required": "true", "Mask": "false"}}, "Device": {}, "Label": {}}}