{"Name": "xware", "Repository": "caiguai/docker-xware", "Registry": "https://hub.docker.com/r/caiguai/docker-xware", "Network": "bridge", "Privileged": "false", "Project": "https://hub.docker.com/r/caiguai/docker-xware", "Overview": "This is a docker image of Thunder downloader.\r\n", "WebUI": "http://yuancheng.xunlei.com", "TemplateURL": "https://raw.githubusercontent.com/L1cardo/Unraid-Templates/master/xware/xware.xml", "Icon": "https://yuancheng.xunlei.com/img/tutor/xlly.png", "ExtraParams": "--restart always", "PostArgs": "", "Networking": {"Mode": "bridge"}, "CategoryList": ["Downloaders"], "Sources": ["https://hub.docker.com/r/caiguai/docker-xware", "https://hub.docker.com/r/caiguai/docker-xware"], "Keywords": ["xware"], "Config": {"Port": {}, "Variable": {}, "Path": {"Host Path 1": {"value": "/mnt/user/media/Movie/", "Name": "Host Path 1", "Target": "/xware/TDDOWNLOAD", "Default": "", "Mode": "rw", "Description": "\u5bb9\u5668 Path: /xware/TDDOWNLOAD", "Type": "Path", "Display": "always", "Required": "true", "Mask": "false"}}, "Device": {}, "Label": {}}}