{"Name": "nut-influxdb-exporter", "Repository": "maihai/nut-influxdb-exporter", "Registry": "https://hub.docker.com/r/maihai/nut-influxdb-exporter", "Network": "bridge", "Privileged": "false", "Overview": "Docker wrapper for a Python script to query NUT - Network UPS Tools via a Python script and then send the results to InfluxDB for storage.", "WebUI": "", "Icon": "https://raw.githubusercontent.com/kiwimato/nut-influxdb-exporter/master/assets/nut.png", "PostArgs": "", "Networking": {"Mode": "bridge"}, "CategoryList": ["Tools-Utilities"], "Sources": ["https://github.com/kiwimato/nut-influxdb-exporter", "https://hub.docker.com/r/maihai/nut-influxdb-exporter"], "Keywords": ["nut-influxdb-exporter", ["Tools-Utilities"]], "Requires": " Influxdb (autoadd) exporter app (autoadd)", "Tag": "latest", "Config": {"Device": {}, "Label": {}, "Variable": {"hostname": {"value": "unraid-ups", "Name": "HOSTNAME", "Target": "HOSTNAME", "Default": "unraid", "Mode": "", "Description": "host you want the measurements to show up as in InfluxDB", "Type": "Variable", "Display": "always", "Required": "true", "Mask": "false"}, "watts": {"value": "1500", "Name": "WATTS", "Target": "WATTS", "Default": "", "Mode": "", "Description": "If your UPS doesn't have the nominal power metric then specify the rated watts so that the load percentage can be used to calculate the current watts", "Type": "Variable", "Display": "always", "Required": "false", "Mask": "false"}, "influxdb_host": {"value": "127.0.0.1", "Name": "INFLUXDB_HOST", "Target": "INFLUXDB_HOST", "Default": "localhost", "Mode": "", "Description": "IP address of influxdb", "Type": "Variable", "Display": "always", "Required": "true", "Mask": "false"}, "influxdb_port": {"value": "8086", "Name": "INFLUXDB_PORT", "Target": "INFLUXDB_PORT", "Default": "8086", "Mode": "", "Description": "Container Variable: INFLUXDB_PORT", "Type": "Variable", "Display": "advanced", "Required": "true", "Mask": "false"}, "influxdb_database": {"value": "nut", "Name": "INFLUXDB_DATABASE", "Target": "INFLUXDB_DATABASE", "Default": "nut", "Mode": "", "Description": "InfluxDB database name to store the values", "Type": "Variable", "Display": "advanced", "Required": "true", "Mask": "false"}, "influxdb_user": {"value": "", "Name": "INFLUXDB_USER", "Target": "INFLUXDB_USER", "Default": "", "Mode": "", "Description": "User name for Influxdb", "Type": "Variable", "Display": "advanced-hide", "Required": "false", "Mask": "false"}, "influxdb_password": {"value": "", "Name": "INFLUXDB_PASSWORD", "Target": "INFLUXDB_PASSWORD", "Default": "", "Mode": "", "Description": "Password for Influxdb", "Type": "Variable", "Display": "advanced-hide", "Required": "false", "Mask": "false"}, "nut_host": {"value": "127.0.0.1", "Name": "NUT_HOST", "Target": "NUT_HOST", "Default": "127.0.0.1", "Mode": "", "Description": "NUT hostname", "Type": "Variable", "Display": "advanced", "Required": "true", "Mask": "false"}, "nut_port": {"value": "", "Name": "NUT_PORT", "Target": "NUT_PORT", "Default": "", "Mode": "", "Description": "NUT Port", "Type": "Variable", "Display": "advanced-hide", "Required": "false", "Mask": "false"}, "ups_name": {"value": "", "Name": "UPS_NAME", "Target": "UPS_NAME", "Default": "ups", "Mode": "", "Description": "NUT UPS name", "Type": "Variable", "Display": "advanced-hide", "Required": "false", "Mask": "false"}, "nut_username": {"value": "", "Name": "NUT_USERNAME", "Target": "NUT_USERNAME", "Default": "", "Mode": "", "Description": "Username for NUT", "Type": "Variable", "Display": "advanced-hide", "Required": "false", "Mask": "false"}, "nut_password": {"value": "", "Name": "NUT_PASSWORD", "Target": "NUT_PASSWORD", "Default": "", "Mode": "", "Description": "Password for NUT", "Type": "Variable", "Display": "advanced-hide", "Required": "false", "Mask": "false"}, "debuggingoutput": {"value": "false", "Name": "Debugging Output", "Target": "VERBOSE", "Default": "false", "Mode": "", "Description": "Set this variable to true to see the output in the docker log.", "Type": "Variable", "Display": "advanced", "Required": "false", "Mask": "false"}}, "Path": {}, "Port": {}}}